{
  "subject": "GRB140215A: Continued Discovery Channel Telescope Observations",
  "eventId": "GRB 140215A",
  "bibcode": "2014GCN.15850....1T",
  "createdOn": 1392574116000,
  "circularId": 15850,
  "submitter": "Vicki Toy at UMD  <vtoy@astro.umd.edu>",
  "email": "vtoy@astro.umd.edu",
  "body": "V. Toy (UMD), S.B. Cenko (NASA-GSFC), A. Kutyrev (NASA-GSFC), J. Capone\n(UMD), E. Troja (NASA-GSFC), A. Cucchiara (NASA-GSFC), S. Veilleux (UMD),\nand S. Gezari (UMD) report on behalf of a larger collaboration:\n\nWe re-observed the bright optical afterglow of GRB140215A (Swift trigger\n586680, Markwardt et al., GCN 15837, Cenko et al., GCN 15840) with the\nLarge Monolithic Imager (LMI) on the 4.3m Discovery Channel Telescope (DCT)\nat Happy Jack, AZ from 2014/02/16 2:55 to 2014/02/16 4:05 UTC (0.95-1.0\ndays after the Swift-BAT trigger) in the g',r',i', and z' filters.\n\nCompared with our previous observations, the afterglow continues to follow\nan unbroken power law with decay index of alpha=-1.20 in all filters\n(Perley et al., GCN 15844, and Elenin et al., GCN 15846), consistent with\nthe simultaneous temporal decay observed in the X-rays (Page et al., GCN\n15845).  Specifically we measure r' = 21.6 mag (AB) at a time of 23.5 hr\nafter the trigger, calibrating relative to USNO-B1.\n\nWe thank the entire staff of the Discovery Channel Telescope for assistance\nwith these observations."
}