{
  "subject": "GRB 210722A: Swift detection of a burst with a bright optical counterpart",
  "eventId": "GRB 210722A",
  "bibcode": "2021GCN.30475....1D",
  "createdOn": 1626988423000,
  "circularId": 30475,
  "submitter": "David Palmer at LANL  <palmer@lanl.gov>",
  "email": "palmer@lanl.gov",
  "body": "P. D'Avanzo (INAF-OAB), A. Y. Lien (GSFC/UMBC),\nF. E. Marshall (NASA/GSFC), A. Melandri (INAF-OAB), M. J. Moss (GWU),\nD. M. Palmer (LANL) and A. Tohuvavohu (U Toronto) report on behalf of\nthe Neil Gehrels Swift Observatory Team:\n\nAt 20:54:42 UT, the Swift Burst Alert Telescope (BAT) triggered and\nlocated GRB 210722A (trigger=1061223).  Swift slewed immediately to the burst. \nThe BAT on-board calculated location is \nRA, Dec 27.023, -6.354 which is \n   RA(J2000) = 01h 48m 06s\n   Dec(J2000) = -06d 21' 14\"\nwith an uncertainty of 3 arcmin (radius, 90% containment, including \nsystematic uncertainty).  The BAT light curve showed a complex\nstructure with a duration of about 30 sec.  The peak count rate\nwas ~1500 counts/sec (15-350 keV), at ~0 sec after the trigger. \n\nUsing promptly downlinked XRT data we find an uncatalogued X-ray source located\nat RA, Dec 27.028, -6.345 which is equivalent to:\n   RA(J2000)  = +01h 48m 06.84\n   Dec(J2000) = -06d 20' 42.7\"\nwith an uncertainty of 5.0 arcseconds (radius, 90% containment). \n\nUVOT took a finding chart exposure of 150 seconds with the White filter\nstarting 94 seconds after the BAT trigger. There is a candidate afterglow in\nthe rapidly available 2.7'x2.7' sub-image at\nRA(J2000) = 01:48:07.27 = 27.03028\nDEC(J2000) = -06:20:49.8 = -6.34718\nwith a 90%-confidence error radius of about 0.74 arc sec. This position is 9.6\narc sec. from the center of the XRT error circle. The estimated magnitude is\n14.37 with a 1-sigma error of about 0.14. No correction has been made for the\nexpected extinction corresponding to E(B-V) of 0.027. \n\nBurst Advocate for this burst is P. D'Avanzo (paolo.davanzo AT inaf.it). \nPlease contact the BA by email if you require additional information\nregarding Swift followup of this burst. In extremely urgent cases, after\ntrying the Burst Advocate, you can contact the Swift PI by phone (see\nSwift TOO web site for information: http://www.swift.psu.edu/)"
}