{
  "editedOn": 1724257235669,
  "subject": "GRB 240819A: KAIT optical upper limit",
  "version": 2,
  "eventId": "GRB 240819A",
  "submittedHow": "email-legacy",
  "bibcode": "2024GCN.37213....1Z",
  "createdOn": 1724206596142,
  "editedBy": "Vidushi Sharma at NASA GSFC/UMBC <vidushi.sharma@nasa.gov> on behalf of Weikang Zheng at UC Berkeley <weikang@berkeley.edu>",
  "circularId": 37213,
  "submitter": "Weikang Zheng at UC Berkeley <weikang@berkeley.edu>",
  "format": "text/plain",
  "body": "WeiKang Zheng, Alexei V. Filippenko (UCB) and S. Antier (OCA),\n\n\nSVOM JSWG: Jian-Yan Wei (NAOC, China), Bertrand Cordier (CEA, F),\n\nShuang-Nan Zhang (IHEP, CN), Stephane Basa (LAM, F), Jean-Luc Attéia\n\n(IRAP, F), Arnaud Claret (CEA, F), Zi-Gao Dai (USTC, CN), Frederic Daigne\n\n(IAP, F), Jin-Song Deng (NAOC, CN), Andrea Goldwurm (APC, F),\n\nDiego  Götz (CEA, F), Xu-Hui Han (NAOC, CN), Cyril Lachaud (APC, F),\n\nEn-Wei Liang (GXU, CN), Yu-Lei Qiu (NAOC, CN), Susanna Vergani\n\n(Obs. Paris, F), Jing Wang (NAOC, CN), Chao Wu (NAOC, CN), Li-Ping Xin\n\n(NAOC, CN), Bing Zhang (UNLV, CN)\n\n\nreport on behalf of the KAIT GRB team:\n\n\nThe 0.76-m Katzman Automatic Imaging Telescope (KAIT), located at\n\nLick Observatory, responded to GRB 240819A from the SVOM/ECLAIRs\n\ntrigger sb24081901 (Coleiro et al., GCN 37208) starting at 03:49\n\nUT, Aug 19th, ~1.23 hours after the trigger. Observations were\n\nperformed in 3x3 tiling mode and lasted for about 6 hours, a set\n\nof clear (roughly R) filter images were obtained. The location of\n\nthe 4 X-ray sources, two from Swift XRT (Evans et al., GCN 37203)\n\nand two additional ones from EP/FXT (Li et al., GCN 37206) were all\n\ncovered in our images. Preliminary analysis do not reveal any new\n\noptical counterpart candidate within the X-ray error circles,\n\nneither in single image, nor in the co-add images, consistent with\n\nthe reports from Jiang et al. (GCN 37207). The typical limiting\n\nmagnitude of our single clear image is about 19.5 mag calibrated to\n\nthe Pan-STARRS1 catalog.\n"
}