{
  "subject": "EP241021a: ATCA radio observations",
  "eventId": "EP241021a",
  "submittedHow": "web",
  "bibcode": "2024GCN.37949....1R",
  "createdOn": 1730244830913,
  "submitter": "Roberto Ricci at INAF-IRA <ricci@ira.inaf.it>",
  "circularId": 37949,
  "format": "text/plain",
  "body": "R. Ricci (U Rome/INAF-IRA), G. Bruni (INAF-IAPS), F. Carotenuto (U Oxford), , G. Gianfagna (INAF-IAPS), Y. Yao (UC Berkeley) on behalf of a larger group:  \n\nWe observed the Fast X-ray Transient EP241021a discovered by Einstein Probe (Hu et al. GCN 37834; Wang et al. GCN 37848) at the optical counterpart position (Fu et al. 37840) with the Australia Telescope Compact Array at 5.5 and 9 GHz in continuum mode on Oct 29th 11:00-18:00 UT (i.e. 8.40 days after the EP trigger) under four independent projects.\n\nA bright source was detected at 5.5 GHz with with a flux density of 400 +/- 20 microJy\nat the OT position. The rms noise in the final map is 13 microJy/beam.   \n\nFurther observations are planned.\n\nThe observers thank the ATCA staff for promptly scheduling the observations.\n"
}