{
  "subject": "EP241113a: Non-detection in Radio Follow-up Observations with eMERLIN",
  "eventId": "EP241113a",
  "submittedHow": "web",
  "bibcode": "2024GCN.38659....1W",
  "createdOn": 1735009249002,
  "submitter": "Tao An at SHAO, CAS <antao@shao.ac.cn>",
  "circularId": 38659,
  "format": "text/plain",
  "body": "Ailing Wang (IHEP, China), Tao An (SHAO, China), Cuiyuan Dai, Xiang-Yu Wang (Nanjing University, China), on behalf of the EP radio follow-up team:\n \nWe report radio follow-up observations of EP241113a, which was initially discovered by the EP team (Liu et al., GCN 38211). A candidate optical counterpart was subsequently identified by Rossi et al. (GCN 38233), with a tentative redshift of z ~ 1.5 (Quirola-Vasquez et al., GCN 38449). We conducted follow-up observations using the enhanced Multi Element Remotely Linked Interferometer Network (eMERLIN).\n\nOur observations targeted the EP/FXT position at R.A. = 131.9964°, DEC = 52.3815° (J2000). The observations were carried out in two epochs:\n1. 2024-11-18 20:00 UTC to 2024-11-19 12:21 UTC\n2. 2024-11-23 08:30 UTC to 2024-11-27 14:49 UTC\n\nNo significant radio emission was detected at 5 GHz in either epoch. We derive 3σ upper limits of:\n- First epoch: 1.0 mJy\n- Second epoch: 0.2 mJy\n\nWe acknowledge the eMERLIN TAC for approving this DDT proposal and the operations team for their rapid scheduling and excellent support.\n"
}