{
  "subject": "GRB 080625: Further observations from OSN",
  "eventId": "GRB 080625",
  "bibcode": "2008GCN..7907....1D",
  "createdOn": 1214465124000,
  "circularId": 7907,
  "submitter": "Antonio Deugarte at IAA-CSIC  <deugarte@iaa.es>",
  "email": "deugarte@iaa.es",
  "body": "A. de Ugarte Postigo (ESO), F. Aceituno,\nA.J. Castro-Tirado, J. Gorosabel (IAA-CSIC)\nreport on behalf of a larger collaboration:\n\nWe have observed again the field of GRB 080625 (Pacciani et al.\nGCN 7903) using the 1.5m OSN telescope at Sierra Nevada\nObservatory (Granada, Spain) at a mean epoch of 14.76h after the\nburst. The object identified by Immler et al. (GCN 7905) is well\ndetected in this and in our previous epoch (GCN 7904). A preliminary\nphotometry against USNO-B1.0 stars shows the object decaying, as\nseen in the following table:\n\nt-t0 (hours)  Exp (s)   I mag\n8.325           4x300    19.3+/-0.2\n14.769         3x300    20.0+/-0.2"
}